google_services_client_api/__init__.py
google_services_client_api/src/__init__.py
google_services_client_api/src/models/__init__.py
google_services_client_api/src/models/factory/__init__.py
google_services_client_api/src/models/factory/google_account_factory.py
google_services_client_api/src/models/google_account/__init__.py
google_services_client_api/src/models/google_account/google_account.py
google_services_client_api/src/models/google_account/google_calendar.py
google_services_client_api/src/models/service_handler/__init__.py
google_services_client_api/src/models/service_handler/oauth_service.py
google_services_client_api/src/models/service_handler/token_loader.py
google_services_client_api/src/settings/__init__.py
google_services_client_api/src/settings/config.py
google_services_client_api/src/settings/packages.py
google_services_client_api/src/utils/__init__.py
google_services_client_api/src/utils/logger.py
google_services_client_api/src/utils/token_validator.py
google_services_client_api-2.0.1.dist-info/METADATA
google_services_client_api-2.0.1.dist-info/WHEEL
google_services_client_api-2.0.1.dist-info/top_level.txt
google_services_client_api-2.0.1.dist-info/RECORD
