Metadata-Version: 2.4
Name: google_services_client_api
Version: 2.0.1
Author: DIACDE - TJGO
License: CC BY-NC-SA 4.0
Requires-Python: >=3.9.4
Dynamic: author
Dynamic: description
Dynamic: description-content-type
Dynamic: license
Dynamic: requires-python
